twelvelabs/__init__.py
twelvelabs/base_client.py
twelvelabs/client.py
twelvelabs/core/__init__.py
twelvelabs/core/api_error.py
twelvelabs/core/client_wrapper.py
twelvelabs/core/datetime_utils.py
twelvelabs/core/file.py
twelvelabs/core/force_multipart.py
twelvelabs/core/http_client.py
twelvelabs/core/http_response.py
twelvelabs/core/jsonable_encoder.py
twelvelabs/core/pagination.py
twelvelabs/core/pydantic_utilities.py
twelvelabs/core/query_encoder.py
twelvelabs/core/remove_none_from_dict.py
twelvelabs/core/request_options.py
twelvelabs/core/serialization.py
twelvelabs/embed/__init__.py
twelvelabs/embed/client.py
twelvelabs/embed/raw_client.py
twelvelabs/embed/tasks/__init__.py
twelvelabs/embed/tasks/client.py
twelvelabs/embed/tasks/raw_client.py
twelvelabs/embed/tasks/types/__init__.py
twelvelabs/embed/tasks/types/tasks_create_request_video_embedding_scope_item.py
twelvelabs/embed/tasks/types/tasks_create_response.py
twelvelabs/embed/tasks/types/tasks_list_response.py
twelvelabs/embed/tasks/types/tasks_list_response_page_info.py
twelvelabs/embed/tasks/types/tasks_retrieve_request_embedding_option_item.py
twelvelabs/embed/tasks/types/tasks_retrieve_response.py
twelvelabs/embed/tasks/types/tasks_retrieve_response_video_embedding.py
twelvelabs/embed/tasks/types/tasks_status_response.py
twelvelabs/embed/tasks/types/tasks_status_response_video_embedding.py
twelvelabs/environment.py
twelvelabs/errors/__init__.py
twelvelabs/errors/bad_request_error.py
twelvelabs/errors/not_found_error.py
twelvelabs/errors/too_many_requests_error.py
twelvelabs/indexes/__init__.py
twelvelabs/indexes/client.py
twelvelabs/indexes/raw_client.py
twelvelabs/indexes/types/__init__.py
twelvelabs/indexes/types/indexes_create_request_models_item.py
twelvelabs/indexes/types/indexes_create_response.py
twelvelabs/indexes/types/indexes_list_response.py
twelvelabs/indexes/videos/__init__.py
twelvelabs/indexes/videos/client.py
twelvelabs/indexes/videos/raw_client.py
twelvelabs-1.0.2.dist-info/METADATA
twelvelabs-1.0.2.dist-info/WHEEL
twelvelabs-1.0.2.dist-info/RECORD
